qubitflow/__init__.py
qubitflow/core.py
qubitflow/quantum.py
qubitflow-0.1.0.dist-info/METADATA
qubitflow-0.1.0.dist-info/WHEEL
qubitflow-0.1.0.dist-info/top_level.txt
qubitflow-0.1.0.dist-info/RECORD
