Metadata-Version: 2.4
Name: qubitflow
Version: 0.1.0
Summary: A modular and scalable quantum computing framework inspired by TensorFlow and PyTorch.
Home-page: https://github.com/qubit-flow/qubitflow
Author: G Sreejith
Author-email: Your Name <you@example.com>
License: MIT
Requires-Python: >=3.8
Requires-Dist: numpy
Requires-Dist: matplotlib
Dynamic: author
Dynamic: home-page
Dynamic: requires-python
